instruwav/__init__.py
instruwav/instrusound.py
instruwav/make_kb_file.py
instruwav/playmusic.py
instruwav/Core/Exceptions.py
instruwav/Core/__config__.py
instruwav/Resources/_config.json
instruwav/Resources/my_keyboard.kb
instruwav/audio_files/bowlStereo_c6.wav
instruwav/audio_files/bowl_c6.wav
instruwav/audio_files/piano_c4.wav
instruwav/audio_files/violin_c4.wav
instruwav/keyboards/azerty_typewriter.txt
instruwav/keyboards/qwerty_piano.txt
instruwav-0.0.0rc0.dist-info/LICENSE.txt
instruwav-0.0.0rc0.dist-info/METADATA
instruwav-0.0.0rc0.dist-info/WHEEL
instruwav-0.0.0rc0.dist-info/entry_points.txt
instruwav-0.0.0rc0.dist-info/top_level.txt
instruwav-0.0.0rc0.dist-info/RECORD
