Metadata-Version: 2.1
Name: instruwav
Version: 0.0.0rc0
Summary: Generate sounds using a base note
Home-page: https://github.com/sclass53/Instruwav
Author: GinoZhang
Maintainer: Gino Zhang
License: see LICENSE.txt
Keywords: keyboard,synthesizer,instrument,music
Platform: UNKNOWN
Classifier: Programming Language :: Python
Classifier: Programming Language :: Python :: 3
Classifier: Intended Audience :: End Users/Desktop
Classifier: Intended Audience :: Education
Classifier: Operating System :: Microsoft :: Windows
Classifier: Operating System :: POSIX
Classifier: Operating System :: MacOS
Classifier: Topic :: Software Development :: Libraries :: Python Modules
Classifier: Topic :: Games/Entertainment :: Simulation
Classifier: Topic :: Multimedia :: Sound/Audio
Classifier: Topic :: Multimedia :: Sound/Audio :: Players
Requires-Python: >=3
License-File: LICENSE.txt
Requires-Dist: librosa (>=0.8.0)
Requires-Dist: pygame (>=2.0.0)
Requires-Dist: keyboardlayout (>=2.0.1)
Requires-Dist: playsound (>=1.0.1)
Provides-Extra: dev
Requires-Dist: setuptools ; extra == 'dev'
Requires-Dist: wheel ; extra == 'dev'
Requires-Dist: twine ; extra == 'dev'
Requires-Dist: isort ; extra == 'dev'
Requires-Dist: black ; extra == 'dev'
